dataverk_tools/__init__.py
dataverk_tools/_doc.py
dataverk_tools/colortools/__init__.py
dataverk_tools/colortools/_utils.py
dataverk_tools/themes/__init__.py
dataverk_tools/themes/_colormaps.py
dataverk_tools/themes/_swatches.py
dataverk_tools/themes/datakatalogen/__init__.py
dataverk_tools/themes/datakatalogen/altair_template.py
dataverk_tools/themes/datakatalogen/colors.py
dataverk_tools/themes/datakatalogen/discrete.py
dataverk_tools/themes/datakatalogen/plotly_template.py
dataverk_tools/themes/datakatalogen/scales.py
dataverk_tools/themes/datakatalogen/sequential.py
dataverk_tools/themes/helserisk/__init__.py
dataverk_tools/themes/helserisk/plotly_template.py
dataverk_tools/themes/nav/__init__.py
dataverk_tools/themes/nav/colors.py
dataverk_tools/themes/nav/discrete.py
dataverk_tools/themes/nav/plotly_template.py
dataverk_tools/themes/nav/sequential.py
dataverk_tools/themes/navdesign/__init__.py
dataverk_tools/themes/navdesign/altair_template.py
dataverk_tools/themes/navdesign/colors.py
dataverk_tools/themes/navdesign/discrete.py
dataverk_tools/themes/navdesign/nav.py
dataverk_tools/themes/navdesign/plotly_template.py
dataverk_tools/themes/navdesign/sequential.py
dataverk_tools-0.1.2.dist-info/METADATA
dataverk_tools-0.1.2.dist-info/WHEEL
dataverk_tools-0.1.2.dist-info/top_level.txt
dataverk_tools-0.1.2.dist-info/RECORD
