Metadata-Version: 2.1
Name: dataverk-tools
Version: 0.1.2
Summary: Theming and colors for dataverker and python dataviz
Home-page: https://github.com/navikt/dataverk_tools/
Author: Paul Bencze
Author-email: paulbencze@nav.no
License: MIT
Project-URL: Github, https://github.com/navikt/dataverk_tools/
Platform: UNKNOWN
Classifier: Development Status :: 4 - Beta
Classifier: License :: OSI Approved :: MIT License
Requires-Dist: plotly
Requires-Dist: altair
Requires-Dist: statsmodels
Requires-Dist: colorlover
Requires-Dist: matplotlib
Requires-Dist: numpy
Requires-Dist: vega
Requires-Dist: vega-datasets
